mcp_reddit/reddit_fetcher.py
mseep_mcp_reddit_server-0.1.1.dist-info/METADATA
mseep_mcp_reddit_server-0.1.1.dist-info/WHEEL
mseep_mcp_reddit_server-0.1.1.dist-info/entry_points.txt
mseep_mcp_reddit_server-0.1.1.dist-info/licenses/LICENSE
mseep_mcp_reddit_server-0.1.1.dist-info/RECORD
