Metadata-Version: 2.4
Name: mseep-mcp-reddit-server
Version: 0.1.1
Summary: Add your description here
Author-email: mseep <support@skydeck.ai>
License-File: LICENSE
Requires-Python: >=3.11
Requires-Dist: dnspython>=2.7.0
Requires-Dist: fastmcp>=0.1.0
Requires-Dist: praw>=7.8.1
Requires-Dist: redditwarp>=1.3.0
Requires-Dist: uvicorn
